nexgenomics/__init__.py
nexgenomics/_internals.py
nexgenomics/agents.py
nexgenomics/agentstore.py
nexgenomics/cli.py
nexgenomics/images.py
nexgenomics/threads.py
nexgenomics/webhook.py
nexgenomics-0.2.3.dist-info/licenses/LICENSE
nexgenomics-0.2.3.dist-info/METADATA
nexgenomics-0.2.3.dist-info/WHEEL
nexgenomics-0.2.3.dist-info/entry_points.txt
nexgenomics-0.2.3.dist-info/top_level.txt
nexgenomics-0.2.3.dist-info/RECORD
