Metadata-Version: 2.4
Name: nexgenomics
Version: 0.2.3
Summary: The official NexGenomics package for Python
Author: Francis Cianfrocca
License: BSD-3-Clause
Project-URL: Homepage, https://github.com/nexgenomics/py-nexgenomics
Classifier: Programming Language :: Python :: 3
Classifier: License :: OSI Approved :: BSD License
Classifier: Operating System :: OS Independent
Requires-Python: >=3.8
License-File: LICENSE
Requires-Dist: requests
Requires-Dist: python-dateutil
Dynamic: license-file
